[
	{
		"pkg": "@byteowls/capacitor-oauth2",
		"classpath": "com.byteowls.capacitor.oauth2.OAuth2ClientPlugin"
	},
	{
		"pkg": "@capacitor/app",
		"classpath": "com.capacitorjs.plugins.app.AppPlugin"
	},
	{
		"pkg": "@capacitor/browser",
		"classpath": "com.capacitorjs.plugins.browser.BrowserPlugin"
	},
	{
		"pkg": "@capacitor/device",
		"classpath": "com.capacitorjs.plugins.device.DevicePlugin"
	},
	{
		"pkg": "@capacitor/filesystem",
		"classpath": "com.capacitorjs.plugins.filesystem.FilesystemPlugin"
	},
	{
		"pkg": "@capacitor/network",
		"classpath": "com.capacitorjs.plugins.network.NetworkPlugin"
	},
	{
		"pkg": "@capacitor/preferences",
		"classpath": "com.capacitorjs.plugins.preferences.PreferencesPlugin"
	},
	{
		"pkg": "@capacitor/share",
		"classpath": "com.capacitorjs.plugins.share.SharePlugin"
	},
	{
		"pkg": "@capacitor/splash-screen",
		"classpath": "com.capacitorjs.plugins.splashscreen.SplashScreenPlugin"
	},
	{
		"pkg": "send-intent",
		"classpath": "de.mindlib.sendIntent.SendIntent"
	}
]
